advancedlogging/__init__.py
advancedlogging/__main__.py
advancedlogging/advancedlogging.py
advancedlogging/cli.py
advancedlogging-0.1.1.dist-info/AUTHORS.rst
advancedlogging-0.1.1.dist-info/LICENSE
advancedlogging-0.1.1.dist-info/METADATA
advancedlogging-0.1.1.dist-info/WHEEL
advancedlogging-0.1.1.dist-info/entry_points.txt
advancedlogging-0.1.1.dist-info/top_level.txt
advancedlogging-0.1.1.dist-info/RECORD
