Metadata-Version: 2.1
Name: advancedlogging
Version: 0.1.1
Summary: Builds futher on python's logging by adding loggers for classes.
Home-page: https://github.com/fonganthonym/python-advancedlogging
Author: Anthony Michael Fong
Author-email: FongAnthonyM@gmail.com
License: MIT
Project-URL: Documentation, https://python-advancedlogging.readthedocs.io/
Project-URL: Changelog, https://python-advancedlogging.readthedocs.io/en/latest/changelog.html
Project-URL: Issue Tracker, https://github.com/fonganthonym/python-advancedlogging/issues
Platform: UNKNOWN
Classifier: Development Status :: 5 - Production/Stable
Classifier: Intended Audience :: Developers
Classifier: License :: OSI Approved :: MIT License
Classifier: Operating System :: Unix
Classifier: Operating System :: POSIX
Classifier: Operating System :: Microsoft :: Windows
Classifier: Programming Language :: Python
Classifier: Programming Language :: Python :: 3
Classifier: Programming Language :: Python :: 3 :: Only
Classifier: Programming Language :: Python :: 3.6
Classifier: Programming Language :: Python :: 3.7
Classifier: Programming Language :: Python :: 3.8
Classifier: Programming Language :: Python :: 3.9
Classifier: Programming Language :: Python :: Implementation :: CPython
Classifier: Programming Language :: Python :: Implementation :: PyPy
Classifier: Topic :: Utilities
Requires-Python: >=3.6
Requires-Dist: dynamicwrapper (>=1.0.0)
Provides-Extra: dev
Requires-Dist: pytest (>=6.2.3) ; extra == 'dev'
